<?xml version="1.0" encoding="UTF-8"?>
<!-- Edited BY JRH ON 2025-05-13 -->
<YealinkIPPhoneBook>
  <Title>Yealink</Title>
  
<Menu Name="A: Wholesale Departments EXT">
    <Unit Name="01: Operator" Phone1="8001" Phone2="" Phone3=""/>
    <Unit Name="02: Accounts Receivable" Phone1="8002" Phone2="" Phone3=""/>
    <Unit Name="03: Accounts Payable" Phone1="8003" Phone2="" Phone3=""/>
    <Unit Name="04: Human Resources" Phone1="8004" Phone2="" Phone3=""/>
    <Unit Name="05: Dispatch &amp; Fleet" Phone1="8005" Phone2="" Phone3=""/>
    <Unit Name="06: Online Sales &amp; Support" Phone1="8006" Phone2="" Phone3=""/>
    <Unit Name="07: IT Support" Phone1="8007" Phone2="" Phone3=""/>
    <Unit Name="08: Purchasing" Phone1="8008" Phone2="" Phone3=""/>
    <Unit Name="09: Sales" Phone1="8009" Phone2="" Phone3=""/>
    <Unit Name="10: Door Shop" Phone1="8010" Phone2="" Phone3=""/>  
</Menu>
 
<Menu Name="B: Store Number EXT">
    <Unit Name="00: Wholesale" Phone1="8000"/>
    <Unit Name="01: Brenham" Phone1="1000"/>
    <Unit Name="02: Bryan" Phone1="2000"/>
    <Unit Name="03: Caldwell" Phone1="3000"/>
    <Unit Name="04: Lexington" Phone1="4000"/>
    <Unit Name="05: Groesbeck" Phone1="5000"/>
    <Unit Name="06: Mexia" Phone1="6000"/>
    <Unit Name="07: Buffalo" Phone1="7000"/>
</Menu> 
  
 <Menu Name="C: Wholesale User EXT">
<!-- Wholesale -->
    <Unit Name="Ann Chapman" Phone1="8103" Phone2="" Phone3=""/>
    <Unit Name="Brian Broaddus" Phone1="8116" Phone2="" Phone3=""/>
    <Unit Name="Cameron McCuller" Phone1="8115" Phone2="" Phone3=""/>		
	<Unit Name="Christy Doss" Phone1="8104" Phone2="" Phone3=""/>
	<Unit Name="Cody Kunkel" Phone1="8111" Phone2="" Phone3=""/>
    <Unit Name="Dana Mondey" Phone1="8101" Phone2="" Phone3=""/>
    <Unit Name="Jason Mitschke" Phone1="8108" Phone2="" Phone3=""/>	
    <Unit Name="Jordan Hejl" Phone1="8110" Phone2="" Phone3=""/>
    <Unit Name="Kate Borroni" Phone1="8105" Phone2="" Phone3=""/>	
	<Unit Name="Kim Rowe" Phone1="8107" Phone2="" Phone3=""/>
    <Unit Name="Lauren Johnson" Phone1="8102" Phone2="" Phone3=""/>
    <Unit Name="Nicholas Braaton" Phone1="8112" Phone2="" Phone3=""/>	
    <Unit Name="Ryneasha Reed" Phone1="8106" Phone2="" Phone3=""/>
    <Unit Name="Stu Chapman" Phone1="8109" Phone2="" Phone3=""/>
    <Unit Name="Sean Rosenbaum" Phone1="8113" Phone2="" Phone3=""/>
    <Unit Name="Troy Mikulin" Phone1="8114" Phone2="" Phone3=""/>
</Menu>
  
<Menu Name="D: Store User EXT">
  <!-- Managers -->
    <Unit Name="Matt Grissom" Phone1="1010" Phone2="" Phone3=""/>
    <Unit Name="Mike Snyder" Phone1="2010" Phone2="" Phone3=""/>
    <Unit Name="James Pieper" Phone1="3010" Phone2="" Phone3=""/>	
    <Unit Name="John Walker" Phone1="4010" Phone2="" Phone3=""/>	
    <Unit Name="JR Noel" Phone1="5010" Phone2="" Phone3=""/>
	<Unit Name="Mexia Manager" Phone1="6010" Phone2="" Phone3=""/>
	<Unit Name="John White" Phone1="7010" Phone2="" Phone3=""/>
	
<!-- Sales Reps -->
    <Unit Name="Anthony Blazek" Phone1="1050" Phone2="" Phone3=""/>
    <Unit Name="Andy Golden" Phone1="2050" Phone2="" Phone3=""/>
	<Unit Name="Cameron McCuller" Phone1="3050" Phone2="" Phone3=""/>
    <Unit Name="Matthew Exner" Phone1="4050" Phone2="" Phone3=""/>
    <Unit Name="Craig Mullen" Phone1="5050" Phone2="" Phone3=""/>
    <Unit Name="Bobby Doak" Phone1="7050" Phone2="" Phone3=""/>

<!-- Asst Managers -->
    <Unit Name="Joseph Lopez" Phone1="3020" Phone2="" Phone3=""/>
    <Unit Name="Robert Hines" Phone1="5020" Phone2="" Phone3=""/>
    <Unit Name="Kasey Payne" Phone1="6020" Phone2="" Phone3=""/>
    <Unit Name="Donna Dickson" Phone1="7020" Phone2="" Phone3=""/>

<!-- Other -->	
    <Unit Name="Jen Bishop" Phone1="2030" Phone2="" Phone3=""/>	
    <Unit Name="Terri Perry" Phone1="5030" Phone2="" Phone3=""/>
</Menu>

<Menu Name="E: Employees (CELL PHONE #)">
  		<Unit Name="[CELL] Ann Chapman" Phone1="+19798202135" Phone2="" Phone3=""/>
		<Unit Name="[CELL] Brian Broaddus" Phone1="+19792190195" Phone2="" Phone3=""/>
		<Unit Name="[CELL] Cameron McCuller" Phone1="+19798203442" Phone2="" Phone3=""/>
		<Unit Name="[CELL] Cody Kunkel" Phone1="+19794515188" Phone2="" Phone3=""/>
		<Unit Name="[CELL] Dana Mondey" Phone1="+19794060082" Phone2="" Phone3=""/>
		<Unit Name="[CELL] Jason Mitschke" Phone1="+19797771366" Phone2="" Phone3=""/>
		<Unit Name="[CELL] Jordan Hejl" Phone1="+19792184176" Phone2="" Phone3=""/>
		<Unit Name="[CELL] Kate Borroni" Phone1="+19792185438" Phone2="" Phone3=""/>
		<Unit Name="[CELL] Lauren Johnson" Phone1="+19794503930" Phone2="" Phone3=""/>
		<Unit Name="[CELL] Kim Rowe" Phone1="+19792297363" Phone2="" Phone3=""/>
		<Unit Name="[CELL] Nicholas Braaton" Phone1="+19792293812" Phone2="" Phone3=""/>
		<Unit Name="[CELL] Sean Rosenbaum" Phone1="+19794519125" Phone2="" Phone3=""/>
		<Unit Name="[CELL] Stu Chapman" Phone1="+16823519062" Phone2="" Phone3=""/>
		<Unit Name="[CELL] Troy Mikulin" Phone1="+19794122386" Phone2="" Phone3=""/>

		<Unit Name="[CELL] Anthony Blazek" Phone1="+19032080155" Phone2="" Phone3=""/>
		<Unit Name="[CELL] Andy Golden" Phone1="+19798201783" Phone2="" Phone3=""/>
		<Unit Name="[CELL] Cameron McCuller" Phone1="+19798203442" Phone2="" Phone3=""/>
		<Unit Name="[CELL] Matt Exner" Phone1="+19795400888" Phone2="" Phone3=""/>
		<Unit Name="[CELL] Craig Mullen" Phone1="+19036448409" Phone2="" Phone3=""/>
		<Unit Name="[CELL] Bobby Doak" Phone1="+19032080418" Phone2="" Phone3=""/>

		<Unit Name="[CELL] Matthew Grissom" Phone1="+17134028614" Phone2="" Phone3=""/>
		<Unit Name="[CELL] Mike Snyder" Phone1="+12703196066" Phone2="" Phone3=""/>
		<Unit Name="[CELL] James Pieper" Phone1="+19793244789" Phone2="" Phone3=""/>
		<Unit Name="[CELL] John Walker" Phone1="+15124300187" Phone2="" Phone3=""/>
		<Unit Name="[CELL] JR Noel" Phone1="+12542242010" Phone2="" Phone3=""/>
		<Unit Name="[CELL] Mexia Manager" Phone1="+12542242010" Phone2="" Phone3=""/>
		<Unit Name="[CELL] John White" Phone1="+19196717159" Phone2="" Phone3=""/>

		<Unit Name="[CELL] Jen Bishop" Phone1="+19035124543" Phone2="" Phone3=""/>
		<Unit Name="[CELL] Joseph Lopez" Phone1="+19792292382" Phone2="" Phone3=""/>
		<Unit Name="[CELL] Josh Lay" Phone1="+19795408626" Phone2="" Phone3=""/>
		<Unit Name="[CELL] Donna Dickson" Phone1="+19365813865" Phone2="" Phone3=""/>
  </Menu>

</YealinkIPPhoneBook>
